midich/__init__.py
midich/args.py
midich/config.py
midich/main.py
midich/core/__init__.py
midich/core/deck.py
midich/core/exceptions.py
midich/core/rules.py
midich/utils/__init__.py
cat_midich-0.1.2.dist-info/METADATA
cat_midich-0.1.2.dist-info/WHEEL
cat_midich-0.1.2.dist-info/entry_points.txt
cat_midich-0.1.2.dist-info/top_level.txt
cat_midich-0.1.2.dist-info/RECORD
