Metadata-Version: 2.4
Name: cat-midich
Version: 0.1.2
Summary: Консольный расклад по системе Мидичи
Author-email: Akio <lazzycatto@yandex.com>
Requires-Python: >=3.8
Requires-Dist: termcolor
